fancybox/__init__.py
fancybox/models.py
fancybox/static/fancybox/css/jquery.fancybox.min.css
fancybox/static/fancybox/js/jquery.fancybox.min.js
fancybox/templates/fancybox/base.html
fancybox/templates/fancybox/fancybox_css.html
fancybox/templates/fancybox/fancybox_js.html
django_fancybox-0.1.6.dist-info/LICENSE
django_fancybox-0.1.6.dist-info/METADATA
django_fancybox-0.1.6.dist-info/WHEEL
django_fancybox-0.1.6.dist-info/top_level.txt
django_fancybox-0.1.6.dist-info/RECORD
