Metadata-Version: 1.1
Name: django-fancybox
Version: 0.1.6
Summary: Simple fancybox modal for Django
Home-page: https://github.com/bashu/django-fancybox
Author: Basil Shubin
Author-email: basil.shubin@gmail.com
License: BSD License
Download-URL: https://github.com/bashu/django-fancybox/zipball/master
Platform: UNKNOWN
Classifier: Development Status :: 5 - Production/Stable
Classifier: Environment :: Web Environment
Classifier: Framework :: Django
Classifier: Intended Audience :: Developers
Classifier: License :: OSI Approved :: BSD License
Classifier: Operating System :: OS Independent
Classifier: Programming Language :: Python
Classifier: Programming Language :: Python :: 2
Classifier: Programming Language :: Python :: 2.7
Classifier: Programming Language :: Python :: 3
Classifier: Programming Language :: Python :: 3.4
Classifier: Topic :: Internet :: WWW/HTTP
Classifier: Topic :: Internet :: WWW/HTTP :: Dynamic Content
Requires: Django (>=1.4)
